{"stats":{"minecraft:used":{"minecraft:redstone_torch":1,"minecraft:wheat_seeds":21,"minecraft:water_bucket":2,"minecraft:end_rod":2,"minecraft:golden_hoe":34,"minecraft:crafting_table":1,"minecraft:stripped_birch_log":1,"minecraft:grass_block":36,"minecraft:redstone":2,"goldengalore:golden_bread":1,"minecraft:potato":18,"goldengalore:golden_sugar_block":28,"minecraft:redstone_block":1,"minecraft:bone_meal":84},"minecraft:picked_up":{"goldengalore:golden_sugar":1,"minecraft:golden_helmet":1,"minecraft:wheat":20,"minecraft:wheat_seeds":50,"goldengalore:midas_crown":6,"minecraft:potato":55},"minecraft:mined":{"minecraft:potatoes":14,"minecraft:wheat":20},"minecraft:custom":{"minecraft:time_since_rest":68786,"minecraft:damage_taken":31,"minecraft:sprint_one_cm":14521,"minecraft:play_time":68786,"minecraft:damage_absorbed":40,"minecraft:walk_one_cm":34655,"minecraft:sneak_time":4,"minecraft:drop":8,"minecraft:jump":142,"minecraft:leave_game":34,"minecraft:time_since_death":68786,"minecraft:climb_one_cm":60,"minecraft:total_world_time":196524,"minecraft:interact_with_crafting_table":8,"minecraft:fall_one_cm":3135,"minecraft:fly_one_cm":46266},"minecraft:dropped":{"goldengalore:midas_crown":6,"minecraft:golden_helmet":1,"goldengalore:golden_sugar":1}},"DataVersion":3465}